{
    "AppProtocolVersion": "200360/AB2da648b9154F2cCcAFBD85e0Bc3d51f97330Fc/MEUCIQDvaEtWlUXkLYIVwIInB25Ff1Ex+kY5b.aECcgLkFt6XgIgHi16XLCgMdNdTu7tvCYGLuZsTlt7eBxL9A6FyfhP7yE=/ZHU5OnRpbWVzdGFtcHUxMDoyMDI1LTA5LTIzZQ==",
    "PlanetRegistryUrl": "https://planets-internal.nine-chronicles.com/planets/",
    "DefaultPlanetId": "0x100000000001",
    "StateRestoreUrl": "https://backoffice.nine-chronicles.com/api/AddressStateAction/create-set-address-state-transaction",

    "NoMiner": true,
    "RpcClient": true,
    "RpcServerHost": "empty",
    "RpcServerPort": 0,

    "MeadPledgePortalUrl": "https://developer-mode.nine-chronicles.com",
    "IAPServiceHost": "https://iap-internal-api.9c.gg",
    "SeasonPassServiceHost": "https://seasonpass-internal.9c.gg",

    "SheetBucketUrl": "https://sheets.libplanet.io",

    "AppleMarketUrl" : "https://apps.apple.com/app/%EB%82%98%EC%9D%B8-%ED%81%AC%EB%A1%9C%EB%8B%88%ED%81%B4-k/id6502042416",
    "GoogleMarketUrl" : "https://play.google.com/store/apps/details?id=com.planetariumlabs.ninechroniclesmobilek",

    "maintenance" : true,
    "EnableGuestLogin" : true,
    "ingameDebugConsole" : false,

    "MixpanelDebugError" : false,
    "MixpanelDebugAssert" : false,
    "MixpanelDebugException" : false,
    "MixpanelDebugWarning" : false
}
